itslit/__init__.py
itslit/__version__.py
itslit/cli.py
itslit/data/lightning_talks
itslit-0.1.2.dist-info/LICENSE
itslit-0.1.2.dist-info/METADATA
itslit-0.1.2.dist-info/WHEEL
itslit-0.1.2.dist-info/entry_points.txt
itslit-0.1.2.dist-info/top_level.txt
itslit-0.1.2.dist-info/RECORD
